{
  "project_info": {
    "project_number": "604233061852",
    "firebase_url": "https://casagrande-b9a87.firebaseio.com",
    "project_id": "casagrande-b9a87",
    "storage_bucket": "casagrande-b9a87.appspot.com"
  },
  "client": [
    {
      "client_info": {
        "mobilesdk_app_id": "1:604233061852:android:5442e20160be8eb7d46b19",
        "android_client_info": {
          "package_name": "com.bytheg.byh16m"
        }
      },
      "oauth_client": [
        {
          "client_id": "604233061852-6ee3ejdrtqt06dmr6oduf117saag0vl8.apps.googleusercontent.com",
          "client_type": 3
        }
      ],
      "api_key": [
        {
          "current_key": "AIzaSyDqz7Iw_tSAoECBc7ojkIUGofBa_INc8O0"
        }
      ],
      "services": {
        "appinvite_service": {
          "other_platform_oauth_client": [
            {
              "client_id": "604233061852-6ee3ejdrtqt06dmr6oduf117saag0vl8.apps.googleusercontent.com",
              "client_type": 3
            }
          ]
        }
      }
    }
  ],
  "configuration_version": "1"
}